polarify/__init__.py
polarify/main.py
polarify-0.2.1.dist-info/METADATA
polarify-0.2.1.dist-info/WHEEL
polarify-0.2.1.dist-info/licenses/LICENSE
polarify-0.2.1.dist-info/RECORD
