Metadata-Version: 2.4
Name: polarify
Version: 0.2.1
Summary: Simplifying conditional Polars Expressions with Python 🐍 🐻‍❄️
Project-URL: Homepage, https://github.com/quantco/polarify
Author-email: Bela Stoyan <bela.stoyan@quantco.com>, Pavel Zwerschke <pavel.zwerschke@quantco.com>
License: Copyright 2023 QuantCo Inc, Pavel Zwerschke, Bela Stoyan
License-File: LICENSE
Classifier: Programming Language :: Python :: 3
Classifier: Programming Language :: Python :: 3.9
Classifier: Programming Language :: Python :: 3.10
Classifier: Programming Language :: Python :: 3.11
Classifier: Programming Language :: Python :: 3.12
Classifier: Programming Language :: Python :: 3.13
Requires-Python: >=3.9
Requires-Dist: polars<2,>=0.14.24
